Workbook
Name SlicerCache_Table_1_Col_2: #N/A
Name SlicerCache_Table_1_Col_5: #N/A
Name SlicerCache_Table_1_Col_7: #N/A

Sheet Sales_Data
A1: Sales ID | B1: Product Category | C1: Units Sold | D1: Unit Price | E1: Salesperson | F1: Date | G1: Region | H1: Revenue
A2: S001 | B2: Software | C2: 15 | D2: 120 | E2: Ana Cruz | F2: 46025 | G2: East | H2: =C2*D2 -> 1800
A3: S002 | B3: Hardware | C3: 8 | D3: 250 | E3: John Lee | F3: 46026 | G3: West | H3: =C3*D3 -> 2000
A4: S003 | B4: Subscription | C4: 30 | D4: 40 | E4: Maria Santos | F4: 46027 | G4: South | H4: =C4*D4 -> 1200
A5: S004 | B5: Accessories | C5: 25 | D5: 15 | E5: David Kim | F5: 46028 | G5: North | H5: =C5*D5 -> 375
A6: S005 | B6: Software | C6: 12 | D6: 150 | E6: Luis Garcia | F6: 46029 | G6: North | H6: =C6*D6 -> 1800
A7: S006 | B7: Hardware | C7: 5 | D7: 300 | E7: Ana Cruz | F7: 46030 | G7: East | H7: =C7*D7 -> 1500
A8: S007 | B8: Subscription | C8: 45 | D8: 35 | E8: John Lee | F8: 46031 | G8: South | H8: =C8*D8 -> 1575
A9: S008 | B9: Accessories | C9: 40 | D9: 20 | E9: Maria Santos | F9: 46032 | G9: West | H9: =C9*D9 -> 800
A10: S009 | B10: Software | C10: 20 | D10: 110 | E10: David Kim | F10: 46033 | G10: North | H10: =C10*D10 -> 2200
A11: S010 | B11: Hardware | C11: 10 | D11: 275 | E11: Luis Garcia | F11: 46034 | G11: East | H11: =C11*D11 -> 2750
A12: S011 | B12: Subscription | C12: 50 | D12: 30 | E12: Ana Cruz | F12: 46035 | G12: East | H12: =C12*D12 -> 1500
A13: S012 | B13: Accessories | C13: 35 | D13: 18 | E13: John Lee | F13: 46036 | G13: East | H13: =C13*D13 -> 630
... A61: S060 | B61: Accessories | C61: 32 | D61: 25 | E61: Luis Garcia | F61: 46085 | G61: West | H61: =C61*D61 -> 800

Sheet Product Reference Table
A1: CATEGORY | B1: PRODUCT | C1: UNIT PRICE (PHP)
A2: SOFTWARE | B2: Antivirus Software License | C2: 120
B3: Project Management Software | C3: 250
B4: Accounting Software | C4: 150
B5: Graphic Design Software | C5: 290
B6: Video Editing Software | C6: 275
A7: HARDWARE | B7: Mechanical Keyboard | C7: 110
B8: Wireless Mouse | C8: 130
B9: External Hard Drive | C9: 260
B10: Gaming Headset | C10: 320
B11: Webcam | C11: 310
A12: SUBSCRIPTION | B12: Cloud Storage Subscription | C12: 40
B13: Online Learning Subscription | C13: 35
B14: Music Streaming Subscription | C14: 30
B15: Video Streaming Subscription | C15: 37
B16: Productivity App Subscription | C16: 33
A17: ACCESSORIES | B17: USB Flash Drive | C17: 20
B18: Phone Charger | C18: 18
B19: Laptop Sleeve | C19: 22
B20: Mouse Pad | C20: 19
B21: HDMI Cable | C21: 24

Sheet Formula and Logic
A1: Total Revenue (SUM) | B1: Average (AVERAGE) | C1: Sale Status (IF) | D1: Region Count (COUNTIF) | E1: Region Names | F1: Sales Tier (NESTED IF) | G1: Salesperson Revenue (SUMIF) | H1: Salesperson Name | I1: Search Sales ID (VLOOKUP) | J1: Product Category (VLOOKUP) | K1: Revenue (VLOOKUP)
A2: =SUM(Sales_Data!H2:H31) -> 47989 | B2: =AVERAGE(Sales_Data!H2:H31) -> 1599.6333 | C2: =IF(Sales_Data!C2>0,"Active","Inactive") -> Active | D2: =COUNTIF(Sales_Data!G2:G31,"North") -> 8 | E2: North | F2: =IF(Sales_Data!H2>=2000,"High",IF(Sales_Data!H2>=1000,"Medium",IF(Sales_Data!H2>0,"Low","No Sale"))) -> Medium | G2: =SUMIF(Sales_Data!$E$2:$E$31,Sales_Data!E2,Sales_Data!$H$2:$H$31) -> 10474 | H2: =Sales_Data!E2 -> Ana Cruz | I2: S059 | J2: =VLOOKUP($I$2,Sales_Data!$A$2:$H$61,2,FALSE) -> Subscription | K2: =VLOOKUP($I$2,Sales_Data!$A$2:$H$61,8,FALSE) -> 1426
B3: =AVERAGE(Sales_Data!H3:H32) -> 1587.7333 | C3: =IF(Sales_Data!C3>0,"Active","Inactive") -> Active | D3: =COUNTIF(Sales_Data!G2:G31,"South") -> 5 | E3: South | F3: =IF(Sales_Data!H3>=2000,"High",IF(Sales_Data!H3>=1000,"Medium",IF(Sales_Data!H3>0,"Low","No Sale"))) -> High | G3: =SUMIF(Sales_Data!$E$2:$E$31,Sales_Data!E3,Sales_Data!$H$2:$H$31) -> 9556 | H3: =Sales_Data!E3 -> John Lee
B4: =AVERAGE(Sales_Data!H4:H33) -> 1541 | C4: =IF(Sales_Data!C4>0,"Active","Inactive") -> Active | D4: =COUNTIF(Sales_Data!G2:G31,"West") -> 7 | E4: West | F4: =IF(Sales_Data!H4>=2000,"High",IF(Sales_Data!H4>=1000,"Medium",IF(Sales_Data!H4>0,"Low","No Sale"))) -> Medium | G4: =SUMIF(Sales_Data!$E$2:$E$31,Sales_Data!E4,Sales_Data!$H$2:$H$31) -> 8801 | H4: =Sales_Data!E4 -> Maria Santos
B5: =AVERAGE(Sales_Data!H5:H34) -> 1563.8333 | C5: =IF(Sales_Data!C5>0,"Active","Inactive") -> Active | D5: =COUNTIF(Sales_Data!G2:G31,"East") -> 10 | E5: East | F5: =IF(Sales_Data!H5>=2000,"High",IF(Sales_Data!H5>=1000,"Medium",IF(Sales_Data!H5>0,"Low","No Sale"))) -> Low | G5: =SUMIF(Sales_Data!$E$2:$E$31,Sales_Data!E5,Sales_Data!$H$2:$H$31) -> 8813 | H5: =Sales_Data!E5 -> David Kim
B6: =AVERAGE(Sales_Data!H6:H35) -> 1639.3333 | C6: =IF(Sales_Data!C6>0,"Active","Inactive") -> Active | F6: =IF(Sales_Data!H6>=2000,"High",IF(Sales_Data!H6>=1000,"Medium",IF(Sales_Data!H6>0,"Low","No Sale"))) -> Medium | G6: =SUMIF(Sales_Data!$E$2:$E$31,Sales_Data!E6,Sales_Data!$H$2:$H$31) -> 10345 | H6: =Sales_Data!E6 -> Luis Garcia
B7: =AVERAGE(Sales_Data!H7:H36) -> 1630.5333 | C7: =IF(Sales_Data!C7>0,"Active","Inactive") -> Active | F7: =IF(Sales_Data!H7>=2000,"High",IF(Sales_Data!H7>=1000,"Medium",IF(Sales_Data!H7>0,"Low","No Sale"))) -> Medium | G7: =SUMIF(Sales_Data!$E$2:$E$31,Sales_Data!E7,Sales_Data!$H$2:$H$31) -> 10474 | H7: =Sales_Data!E7 -> Ana Cruz
B8: =AVERAGE(Sales_Data!H8:H37) -> 1598.6667 | C8: =IF(Sales_Data!C8>0,"Active","Inactive") -> Active | F8: =IF(Sales_Data!H8>=2000,"High",IF(Sales_Data!H8>=1000,"Medium",IF(Sales_Data!H8>0,"Low","No Sale"))) -> Medium | G8: =SUMIF(Sales_Data!$E$2:$E$31,Sales_Data!E8,Sales_Data!$H$2:$H$31) -> 9556 | H8: =Sales_Data!E8 -> John Lee
B9: =AVERAGE(Sales_Data!H9:H38) -> 1634 | C9: =IF(Sales_Data!C9>0,"Active","Inactive") -> Active | F9: =IF(Sales_Data!H9>=2000,"High",IF(Sales_Data!H9>=1000,"Medium",IF(Sales_Data!H9>0,"Low","No Sale"))) -> Low | G9: =SUMIF(Sales_Data!$E$2:$E$31,Sales_Data!E9,Sales_Data!$H$2:$H$31) -> 8801 | H9: =Sales_Data!E9 -> Maria Santos
B10: =AVERAGE(Sales_Data!H10:H39) -> 1719.3333 | C10: =IF(Sales_Data!C10>0,"Active","Inactive") -> Active | F10: =IF(Sales_Data!H10>=2000,"High",IF(Sales_Data!H10>=1000,"Medium",IF(Sales_Data!H10>0,"Low","No Sale"))) -> High | G10: =SUMIF(Sales_Data!$E$2:$E$31,Sales_Data!E10,Sales_Data!$H$2:$H$31) -> 8813 | H10: =Sales_Data!E10 -> David Kim
B11: =AVERAGE(Sales_Data!H11:H40) -> 1685.6333 | C11: =IF(Sales_Data!C11>0,"Active","Inactive") -> Active | F11: =IF(Sales_Data!H11>=2000,"High",IF(Sales_Data!H11>=1000,"Medium",IF(Sales_Data!H11>0,"Low","No Sale"))) -> High | G11: =SUMIF(Sales_Data!$E$2:$E$31,Sales_Data!E11,Sales_Data!$H$2:$H$31) -> 10345 | H11: =Sales_Data!E11 -> Luis Garcia
B12: =AVERAGE(Sales_Data!H12:H41) -> 1618.7667 | C12: =IF(Sales_Data!C12>0,"Active","Inactive") -> Active | F12: =IF(Sales_Data!H12>=2000,"High",IF(Sales_Data!H12>=1000,"Medium",IF(Sales_Data!H12>0,"Low","No Sale"))) -> Medium | G12: =SUMIF(Sales_Data!$E$2:$E$31,Sales_Data!E12,Sales_Data!$H$2:$H$31) -> 10474 | H12: =Sales_Data!E12 -> Ana Cruz
B13: =AVERAGE(Sales_Data!H13:H42) -> 1655.3 | C13: =IF(Sales_Data!C13>0,"Active","Inactive") -> Active | F13: =IF(Sales_Data!H13>=2000,"High",IF(Sales_Data!H13>=1000,"Medium",IF(Sales_Data!H13>0,"Low","No Sale"))) -> Low | G13: =SUMIF(Sales_Data!$E$2:$E$31,Sales_Data!E13,Sales_Data!$H$2:$H$31) -> 9556 | H13: =Sales_Data!E13 -> John Lee
B14: =AVERAGE(Sales_Data!H14:H43) -> 1702.3 | C14: =IF(Sales_Data!C14>0,"Active","Inactive") -> Active | F14: =IF(Sales_Data!H14>=2000,"High",IF(Sales_Data!H14>=1000,"Medium",IF(Sales_Data!H14>0,"Low","No Sale"))) -> High | G14: =SUMIF(Sales_Data!$E$2:$E$31,Sales_Data!E14,Sales_Data!$H$2:$H$31) -> 8801 | H14: =Sales_Data!E14 -> Maria Santos
B15: =AVERAGE(Sales_Data!H15:H44) -> 1665.1 | C15: =IF(Sales_Data!C15>0,"Active","Inactive") -> Active | F15: =IF(Sales_Data!H15>=2000,"High",IF(Sales_Data!H15>=1000,"Medium",IF(Sales_Data!H15>0,"Low","No Sale"))) -> Medium | G15: =SUMIF(Sales_Data!$E$2:$E$31,Sales_Data!E15,Sales_Data!$H$2:$H$31) -> 8813 | H15: =Sales_Data!E15 -> David Kim
B16: =AVERAGE(Sales_Data!H16:H45) -> 1619.7667 | C16: =IF(Sales_Data!C16>0,"Active","Inactive") -> Active | F16: =IF(Sales_Data!H16>=2000,"High",IF(Sales_Data!H16>=1000,"Medium",IF(Sales_Data!H16>0,"Low","No Sale"))) -> Medium | G16: =SUMIF(Sales_Data!$E$2:$E$31,Sales_Data!E16,Sales_Data!$H$2:$H$31) -> 10345 | H16: =Sales_Data!E16 -> Luis Garcia
B17: =AVERAGE(Sales_Data!H17:H46) -> 1680.1667 | C17: =IF(Sales_Data!C17>0,"Active","Inactive") -> Active | F17: =IF(Sales_Data!H17>=2000,"High",IF(Sales_Data!H17>=1000,"Medium",IF(Sales_Data!H17>0,"Low","No Sale"))) -> Low | G17: =SUMIF(Sales_Data!$E$2:$E$31,Sales_Data!E17,Sales_Data!$H$2:$H$31) -> 10474 | H17: =Sales_Data!E17 -> Ana Cruz
... B61: =AVERAGE(Sales_Data!H61:H90) -> 800 | C61: =IF(Sales_Data!C61>0,"Active","Inactive") -> Active | F61: =IF(Sales_Data!H61>=2000,"High",IF(Sales_Data!H61>=1000,"Medium",IF(Sales_Data!H61>0,"Low","No Sale"))) -> Low | G61: =SUMIF(Sales_Data!$E$2:$E$31,Sales_Data!E61,Sales_Data!$H$2:$H$31) -> 10345 | H61: =Sales_Data!E61 -> Luis Garcia

Sheet Analytics Summary
A1: Slicer controls: Filters the raw data processed by all pivot tables
A4: Revenue per region/category
A18: Monthly Trend Summary

Sheet Dashboard
B2: SALES ANALYTICS DASHBOARD
C4: Total Revenue | D4: Average Revenue | E4: Highest Revenue | F4: Lowest Revenue
C5: =SUM('Analytics Summary'!C20:C22) -> 99346 | D5: =AVERAGE('Analytics Summary'!C20:C22) -> 33115.333 | E5: =MAX('Analytics Summary'!C20:C22) -> 48590 | F5: =MIN('Analytics Summary'!C20:C22) -> 6582

Sheet Quality Assurance & Documentati
A1: Project Title: | B1: Laboratory 7: Collaborative Data Management & Analytics Project
A2: Document Audited: | B2: Sales_Data
A3: Quality Assurance & Documentation Officer: | B3: Jude Bernard Anthony L. Ramil
A4: Status: | B4: CLEARED / VERIFIED
A5: I have reviewed the attached sales records named, "Sales_Data" and I have assured that this data is consistent with the project's requirements that was set by the company. This dataset is hereby authorized for use in the Analytics and Visualization as we move on to this phase to another.
A7: Below are the evidences that made this data pass:
A8: Categorization: Products are correctly sorted into Software, Hardware, Subscription, and Accessories for easy pivot table generation.
A9: Data Completeness: All mandatory fields, including Product Category, Units Sold, and Salesperson, are well mandated. Albeit it not being random enough.
A10: Logical Consistency: Revenue figures and "Save Status" (all marked as "Active") align with the expected data distribution for this laboratory.
A11: Format Uniformity: Date structures and currency representations are accepted as presented for the purpose of this mock data exercise.

Sheet Reflections
A1: Each member must write a short paragraph (100–150 words) explaining:
A3: Their assigned role
A5: Challenges faced
A6: One new skill learned
A8: NAME: | B8: Eman Torr G. Berjame | E8: NAME: | F8: Cristal, Mary Kristine Anne L. | I8: NAME: | J8: Lozano, Ianna E. | M8: NAME: | N8: Tasic, Harrel Henry L.
A9: ROLE: | B9: Formula and Logic Specialist | E9: ROLE: | F9: Data Entry & Cleaning Specialist | I9: ROLE: | J9: Assistant Data Entry & Cleaning Specialist | M9: ROLE: | N9: -
A10: REFLECTION | E10: REFLECTION | I10: REFLECTION | M10: REFLECTION
A11: Being the Formula Specialist was more challenging than I expected. I thought it would be simple, but it required a lot of attention to detail. The hardest parts were the nested IF for Sales Tier classification and getting COUNTIF and SUMIF arguments in the right order. VLOOKUP also gave me trouble since our Sales IDs were in text format, so even a small mismatch would return an error. Referencing data across two sheets made things more complicated as well. Overall, it taught me that understanding the data structure matters just as much as knowing the formula itself. Frustrating at times, but worth it once everything worked. | E11: As the Data Entry & Cleaning Specialist, my main role was to create and organize the dataset used in startup sales and revenue analytics. I was responsible for entering the collected data into a structured format and making sure that all information was consistent and properly arranged. I also checked for errors, removed any unnecessary details, and standardized the formatting so that the dataset would be easier to analyze. My contribution helped ensure that the data used by the team was already organized and thoroughly checked. One of the challenges I faced was dealing with inconsistent data formats and making sure that everything is good, which required careful checking and corrections. Through this experience, I learned a new skill in data cleaning and organization, particularly how to maintain consistency and accuracy when handling large amounts of information. | I11: My assigned role was an assistant data entry and cleaning specialist. I mainly had to support the primary data entry specialist by checking and cleaning the spreadsheet after the initial entries were made. I helped review the dataset to make sure the values were consistent, corrected small formatting issues, and added any missing information when needed. My responsibility was mostly to make sure everything looked organized and accurate before the analysis was finalized since I was working after the main entries were already done. I also assisted making comments to make sure the data and formatting are correct. One challenge I faced was carefully reviewing data without overlooking small errors that could affect the results. Through this task, I learned the importance of data cleaning and attention to detail, as well as how even small adjustments in a dataset can improve the overall quality of the analysis. | M11: -
Q18: -
A23: NAME: | B23: Ramil, Jude Bernard Anthony L. | E23: NAME: | F23: Molero, Raffi O. | I23: NAME: | J23: Ariño, Cedric D. | M23: NAME: | N23: Eroy, Derick Lance
A24: ROLE: | B24: Quality Assurance & Documentation Officer | E24: ROLE: | F24: Pivot Specialist | I24: ROLE: | J24: Dashboard Designer | M24: ROLE: | N24: Project Manager
A25: REFLECTION | E25: REFLECTION | I25: REFLECTION | M25: REFLECTION
A26: As a quality assurance and documentation officer. I contributed by creating a clear pass to our Sales_data sheet. I also viewed the datas and any anomalies to point out to my group to keep the data in shape and in quality to be sent, albeit that this is only a mock data, I think it is a good discipline practice to see errors and attend to them immediately as data is tricky and become a “mass” in the crowd to be spotted that easily. One of the challenging parts for me is to seek out the errors in every corner of the present data. I gained a skill to be assured of data quality by becoming some sort of a “error hunter” and then issuing a pass that this report is clear for my group to proceed. I can use this for my future endeavors. | E26: Pivot tables seemed like a complicated concept, but they turned out to be very easy to make. All I had to do was select the whole table, get specific rows and columns, and select what I wanted to see, and the values were very quickly auto-computed for me. Editing them was also quite easy, thanks to Google Sheets' UI. I explored the idea of using filters, but I found that using Slicers to very quickly select which data we want is much faster and more comfortable than individual table filters, in my opinion. Maybe the most difficult part is figuring out how to put multiple of them in the same sheet without accidentally causing overlap when the filters change. This is why I placed the monthly trends at the bottom. For example if we had 5 years' worth of data, my monthly trends table should not be placed above any other tables, because it might grow and overlap other tables, which may cause issues that I don't currently know about. | I26: As the Dashboard Designer, my primary responsibility was to transform our group's processed data into a clear, visually compelling dashboard. I contributed by building the three required charts alongside the summary metrics section. One of the main challenges I encountered was ensuring that all data ranges and formulas were correctly defined so that each chart accurately reflected the dataset. I also had to make sure each chart presented the data in a way that was easy to read and interpret, keeping the layout clean and avoiding visual clutter. Through this experience, I learned how to design a dashboard that balances both accuracy and clarity, which strengthened my overall proficiency in data visualization. | M26: -
